isprime_pypackage/__init__.py
isprime_pypackage/isPrime.py
isprime_pypackage-0.1.0.dist-info/entry_points.txt
isprime_pypackage-0.1.0.dist-info/WHEEL
isprime_pypackage-0.1.0.dist-info/METADATA
isprime_pypackage-0.1.0.dist-info/RECORD
